jsproto/__init__.py
jsproto/jsproto.py
jsproto-0.6.dist-info/licenses/LICENSE
jsproto-0.6.dist-info/METADATA
jsproto-0.6.dist-info/WHEEL
jsproto-0.6.dist-info/top_level.txt
jsproto-0.6.dist-info/RECORD
