Metadata-Version: 2.4
Name: JSProto
Version: 0.6
Summary: use prototype and its gramma in python
Author-email: yjk <mr.yjk@foxmail.com>
License:                                  Apache License
Project-URL: Homepage, https://github.com/yjk114514/prototype
Requires-Python: >=3.7
License-File: LICENSE
Dynamic: license-file
